setup.py
SHICTHRSTimer/__init__.py
SHICTHRSTimer.egg-info/PKG-INFO
SHICTHRSTimer.egg-info/SOURCES.txt
SHICTHRSTimer.egg-info/dependency_links.txt
SHICTHRSTimer.egg-info/not-zip-safe
SHICTHRSTimer.egg-info/requires.txt
SHICTHRSTimer.egg-info/top_level.txt
SHICTHRSTimer/utils/SHRTimer_get_is_within_hours.py
SHICTHRSTimer/utils/SHRTimer_get_pytz_time.py
SHICTHRSTimer/utils/SHRTimer_get_system_time.py
SHICTHRSTimer/utils/SHRTimer_get_time_stamp.py
SHICTHRSTimer/utils/__init__.py